textcloud/MuseoModerno-SemiBold.ttf
textcloud/__init__.py
textcloud/__main__.py
textcloud/_version.py
textcloud/color_from_image.py
textcloud/query_integral_image.cp37-win_amd64.pyd
textcloud/stopwords
textcloud/textcloud.py
textcloud/textcloud_cli.py
textcloud/tokenization.py
textcloud-0.0.3.dist-info/LICENSE
textcloud-0.0.3.dist-info/METADATA
textcloud-0.0.3.dist-info/WHEEL
textcloud-0.0.3.dist-info/entry_points.txt
textcloud-0.0.3.dist-info/top_level.txt
textcloud-0.0.3.dist-info/RECORD
