Metadata-Version: 2.1
Name: textcloud
Version: 0.0.3
Summary: A little text cloud generator, based on AMueller's excellent word cloud
Home-page: https://github.com/eRajsh/text_cloud
Author: Rajesh Prabhu
Author-email: 
License: MIT
Platform: UNKNOWN
Requires-Dist: numpy (>=1.6.1)
Requires-Dist: pillow
Requires-Dist: matplotlib
